CHANGES.txt
COPYRIGHT.txt
CREDITS.txt
LICENSE.txt
MANIFEST.in
README.txt
bootstrap.py
buildout.cfg
setup.py
src/hurry/__init__.py
src/hurry.jquery.egg-info/PKG-INFO
src/hurry.jquery.egg-info/SOURCES.txt
src/hurry.jquery.egg-info/dependency_links.txt
src/hurry.jquery.egg-info/entry_points.txt
src/hurry.jquery.egg-info/namespace_packages.txt
src/hurry.jquery.egg-info/not-zip-safe
src/hurry.jquery.egg-info/requires.txt
src/hurry.jquery.egg-info/top_level.txt
src/hurry/jquery/__init__.py
src/hurry/jquery/_lib.py
src/hurry/jquery/jquery.txt
src/hurry/jquery/prepare.py
src/hurry/jquery/tests.py
src/hurry/jquery/jquery-build/jquery-1.4.3.js
src/hurry/jquery/jquery-build/jquery-1.4.3.min.js