Metadata-Version: 1.0
Name: hurry.jquery
Version: 1.4.3.1
Summary: hurry.resource style resources for jQuery.
Home-page: UNKNOWN
Author: Jan-Wijbrand Kolman
Author-email: jw@n--tree.net
License: ZPL 2.1
Platform: UNKNOWN
